tapi/__init__.py
tapi/__main__.py
tapi/api/__init__.py
tapi/api/base_api.py
tapi/api/constants.py
tapi/api/exceptions.py
tapi/api/logic.py
tapi/cli/__init__.py
tapi/cli/cli.py
tapi/cli/run/__init__.py
tapi/cli/run/command.py
tapi/cli/run/models.py
pytapi-0.1.0.dist-info/LICENSE
pytapi-0.1.0.dist-info/WHEEL
pytapi-0.1.0.dist-info/METADATA
pytapi-0.1.0.dist-info/RECORD
