Metadata-Version: 2.1
Name: pytapi
Version: 0.1.0
Summary: Python no-code API framework. Create REST interfaces from YAML configs
License: MIT
Author: PSauerborn
Author-email: pascal.sauerborn@gmail.com
Requires-Python: >=3.9,<4.0
Classifier: License :: OSI Approved :: MIT License
Classifier: Programming Language :: Python :: 3
Classifier: Programming Language :: Python :: 3.10
Classifier: Programming Language :: Python :: 3.9
Requires-Dist: PyYAML (>=6.0,<7.0)
Requires-Dist: fastapi (>=0.82.0,<0.83.0)
Requires-Dist: rich (>=12.5.1,<13.0.0)
Requires-Dist: typer (>=0.6.1,<0.7.0)
Requires-Dist: uvicorn (>=0.18.3,<0.19.0)
